sefixlines/__init__.py
sefixlines/baseline.py
sefixlines/datasets.py
sefixlines/models.py
sefixlines/utils.py
sefixlines/notebooks/image_classification.ipynb
sefixlines/notebooks/image_regression.ipynb
sefixlines/notebooks/image_semantic_segmentation.ipynb
sefixlines/notebooks/raw.ipynb
sefixlines/notebooks/text_classification.ipynb
sefixlines/notebooks/text_regression.ipynb
sefixlines-0.3.0.dist-info/licenses/LICENSE
sefixlines-0.3.0.dist-info/METADATA
sefixlines-0.3.0.dist-info/WHEEL
sefixlines-0.3.0.dist-info/top_level.txt
sefixlines-0.3.0.dist-info/RECORD
