Metadata-Version: 2.4
Name: sefixlines
Version: 0.3.0
Summary: A tool for quick ML task solving with model training optimization and a wide range of capabilities
Author-email: sefixnep <rodionovs337@gmail.com>
License-Expression: MIT
Project-URL: Homepage, https://pypi.org/project/sefixlines/
Project-URL: Repository, https://github.com/sefixnep/sefixlines
Project-URL: Bug Tracker, https://github.com/sefixnep/sefixlines/issues
Classifier: Programming Language :: Python :: 3
Classifier: Operating System :: OS Independent
Classifier: Topic :: Scientific/Engineering :: Artificial Intelligence
Classifier: Topic :: Scientific/Engineering :: Image Recognition
Classifier: Intended Audience :: Developers
Classifier: Intended Audience :: Science/Research
Requires-Python: >=3.9
License-File: LICENSE
Requires-Dist: torch>=2.0.0
Requires-Dist: torchvision>=0.15.0
Requires-Dist: numpy>=1.21.0
Requires-Dist: pandas>=1.3.0
Requires-Dist: scikit-learn>=1.0.0
Requires-Dist: Pillow>=8.3.0
Requires-Dist: tqdm>=4.62.0
Requires-Dist: matplotlib>=3.4.0
Requires-Dist: seaborn>=0.11.0
Requires-Dist: segmentation-models-pytorch>=0.3.0
Requires-Dist: transformers>=4.30.0
Requires-Dist: albumentations>=2.0.0
Provides-Extra: dev
Requires-Dist: jupyter>=1.0.0; extra == "dev"
Requires-Dist: ipykernel>=6.0.0; extra == "dev"
Dynamic: license-file
